[
  {
    "id": "genki-2-17-new-212",
    "japanese": "失礼します",
    "reading": "しつれいします",
    "meaning": "Excuse me; Sorry to interrupt you",
    "jlptLevel": "N3",
    "partOfSpeech": [],
    "examples": [
      {
        "japanese": "失礼します",
        "reading": "",
        "english": "17"
      }
    ],
    "tags": [
      "n3",
      "lesson-17",
      "genki-2"
    ],
    "lesson": 17,
    "textbook": "genki-2"
  },
  {
    "id": "genki-2-17-new-213",
    "japanese": "赤ちゃん",
    "reading": "あかちゃん",
    "meaning": "baby",
    "jlptLevel": "N4",
    "partOfSpeech": [],
    "examples": [
      {
        "japanese": "赤ちゃん",
        "reading": "",
        "english": "17"
      }
    ],
    "tags": [
      "n4",
      "lesson-17",
      "genki-2"
    ],
    "lesson": 17,
    "textbook": "genki-2"
  },
  {
    "id": "genki-2-17-new-214",
    "japanese": "お客さん",
    "reading": "おきゃくさん",
    "meaning": "guest; vistor; client; customer",
    "jlptLevel": "N4",
    "partOfSpeech": [],
    "examples": [
      {
        "japanese": "お客さん",
        "reading": "",
        "english": "17"
      }
    ],
    "tags": [
      "n4",
      "lesson-17",
      "genki-2"
    ],
    "lesson": 17,
    "textbook": "genki-2"
  },
  {
    "id": "genki-2-17-new-215",
    "japanese": "首相",
    "reading": "しゅしょう",
    "meaning": "prime minister",
    "jlptLevel": "N5",
    "partOfSpeech": [],
    "examples": [
      {
        "japanese": "首相",
        "reading": "",
        "english": "17"
      }
    ],
    "tags": [
      "n5",
      "lesson-17",
      "genki-2"
    ],
    "lesson": 17,
    "textbook": "genki-2"
  },
  {
    "id": "genki-2-17-new-216",
    "japanese": "サラリーマン",
    "reading": "",
    "meaning": "salaryman; office worker",
    "jlptLevel": "N3",
    "partOfSpeech": [],
    "examples": [
      {
        "japanese": "サラリーマン",
        "reading": "",
        "english": "17"
      }
    ],
    "tags": [
      "n3",
      "lesson-17",
      "genki-2"
    ],
    "lesson": 17,
    "textbook": "genki-2"
  },
  {
    "id": "genki-2-17-new-217",
    "japanese": "給料",
    "reading": "きゅうりょう",
    "meaning": "salary",
    "jlptLevel": "N5",
    "partOfSpeech": [],
    "examples": [
      {
        "japanese": "給料",
        "reading": "",
        "english": "17"
      }
    ],
    "tags": [
      "n5",
      "lesson-17",
      "genki-2"
    ],
    "lesson": 17,
    "textbook": "genki-2"
  },
  {
    "id": "genki-2-17-new-218",
    "japanese": "残業",
    "reading": "ざんぎょう",
    "meaning": "overtime work",
    "jlptLevel": "N5",
    "partOfSpeech": [],
    "examples": [
      {
        "japanese": "残業",
        "reading": "",
        "english": "17"
      }
    ],
    "tags": [
      "n5",
      "lesson-17",
      "genki-2"
    ],
    "lesson": 17,
    "textbook": "genki-2"
  },
  {
    "id": "genki-2-17-new-219",
    "japanese": "パンダ",
    "reading": "",
    "meaning": "panda",
    "jlptLevel": "N4",
    "partOfSpeech": [],
    "examples": [
      {
        "japanese": "パンダ",
        "reading": "",
        "english": "17"
      }
    ],
    "tags": [
      "n4",
      "lesson-17",
      "genki-2"
    ],
    "lesson": 17,
    "textbook": "genki-2"
  },
  {
    "id": "genki-2-17-new-220",
    "japanese": "コンタクト（レンズ）",
    "reading": "",
    "meaning": "contact lenses",
    "jlptLevel": "N2",
    "partOfSpeech": [],
    "examples": [
      {
        "japanese": "コンタクト（レンズ）",
        "reading": "",
        "english": "17"
      }
    ],
    "tags": [
      "n2",
      "lesson-17",
      "genki-2"
    ],
    "lesson": 17,
    "textbook": "genki-2"
  },
  {
    "id": "genki-2-17-new-221",
    "japanese": "髭(rare)",
    "reading": "ひげ",
    "meaning": "beard",
    "jlptLevel": "N2",
    "partOfSpeech": [],
    "examples": [
      {
        "japanese": "髭(rare)",
        "reading": "",
        "english": "17"
      }
    ],
    "tags": [
      "n2",
      "lesson-17",
      "genki-2"
    ],
    "lesson": 17,
    "textbook": "genki-2"
  },
  {
    "id": "genki-2-17-new-222",
    "japanese": "ブーツ",
    "reading": "",
    "meaning": "boots",
    "jlptLevel": "N4",
    "partOfSpeech": [],
    "examples": [
      {
        "japanese": "ブーツ",
        "reading": "",
        "english": "17"
      }
    ],
    "tags": [
      "n4",
      "lesson-17",
      "genki-2"
    ],
    "lesson": 17,
    "textbook": "genki-2"
  },
  {
    "id": "genki-2-17-new-223",
    "japanese": "鍵",
    "reading": "かぎ",
    "meaning": "lock; key",
    "jlptLevel": "N5",
    "partOfSpeech": [],
    "examples": [
      {
        "japanese": "鍵",
        "reading": "",
        "english": "17"
      }
    ],
    "tags": [
      "n5",
      "lesson-17",
      "genki-2"
    ],
    "lesson": 17,
    "textbook": "genki-2"
  },
  {
    "id": "genki-2-17-new-224",
    "japanese": "宝くじ",
    "reading": "たからくじ",
    "meaning": "lottery",
    "jlptLevel": "N4",
    "partOfSpeech": [],
    "examples": [
      {
        "japanese": "宝くじ",
        "reading": "",
        "english": "17"
      }
    ],
    "tags": [
      "n4",
      "lesson-17",
      "genki-2"
    ],
    "lesson": 17,
    "textbook": "genki-2"
  },
  {
    "id": "genki-2-17-new-225",
    "japanese": "紙",
    "reading": "かみ",
    "meaning": "paper",
    "jlptLevel": "N5",
    "partOfSpeech": [],
    "examples": [
      {
        "japanese": "紙",
        "reading": "",
        "english": "17"
      }
    ],
    "tags": [
      "n5",
      "lesson-17",
      "genki-2"
    ],
    "lesson": 17,
    "textbook": "genki-2"
  },
  {
    "id": "genki-2-17-new-226",
    "japanese": "スプーン",
    "reading": "",
    "meaning": "spoon",
    "jlptLevel": "N4",
    "partOfSpeech": [],
    "examples": [
      {
        "japanese": "スプーン",
        "reading": "",
        "english": "17"
      }
    ],
    "tags": [
      "n4",
      "lesson-17",
      "genki-2"
    ],
    "lesson": 17,
    "textbook": "genki-2"
  },
  {
    "id": "genki-2-17-new-227",
    "japanese": "お湯",
    "reading": "おゆ",
    "meaning": "hot water",
    "jlptLevel": "N5",
    "partOfSpeech": [],
    "examples": [
      {
        "japanese": "お湯",
        "reading": "",
        "english": "17"
      }
    ],
    "tags": [
      "n5",
      "lesson-17",
      "genki-2"
    ],
    "lesson": 17,
    "textbook": "genki-2"
  },
  {
    "id": "genki-2-17-new-228",
    "japanese": "電子レンジ",
    "reading": "でんしレンジ",
    "meaning": "microwave oven",
    "jlptLevel": "N3",
    "partOfSpeech": [],
    "examples": [
      {
        "japanese": "電子レンジ",
        "reading": "",
        "english": "17"
      }
    ],
    "tags": [
      "n3",
      "lesson-17",
      "genki-2"
    ],
    "lesson": 17,
    "textbook": "genki-2"
  },
  {
    "id": "genki-2-17-new-229",
    "japanese": "ヒーター",
    "reading": "",
    "meaning": "heater",
    "jlptLevel": "N4",
    "partOfSpeech": [],
    "examples": [
      {
        "japanese": "ヒーター",
        "reading": "",
        "english": "17"
      }
    ],
    "tags": [
      "n4",
      "lesson-17",
      "genki-2"
    ],
    "lesson": 17,
    "textbook": "genki-2"
  },
  {
    "id": "genki-2-17-new-230",
    "japanese": "ニュース",
    "reading": "",
    "meaning": "news",
    "jlptLevel": "N4",
    "partOfSpeech": [],
    "examples": [
      {
        "japanese": "ニュース",
        "reading": "",
        "english": "17"
      }
    ],
    "tags": [
      "n4",
      "lesson-17",
      "genki-2"
    ],
    "lesson": 17,
    "textbook": "genki-2"
  },
  {
    "id": "genki-2-17-new-231",
    "japanese": "火事",
    "reading": "かじ",
    "meaning": "fire",
    "jlptLevel": "N5",
    "partOfSpeech": [],
    "examples": [
      {
        "japanese": "火事",
        "reading": "",
        "english": "17"
      }
    ],
    "tags": [
      "n5",
      "lesson-17",
      "genki-2"
    ],
    "lesson": 17,
    "textbook": "genki-2"
  },
  {
    "id": "genki-2-17-new-232",
    "japanese": "旅行会社",
    "reading": "りょこうがいしゃ",
    "meaning": "travel agency",
    "jlptLevel": "N4",
    "partOfSpeech": [],
    "examples": [
      {
        "japanese": "旅行会社",
        "reading": "",
        "english": "17"
      }
    ],
    "tags": [
      "n4",
      "lesson-17",
      "genki-2"
    ],
    "lesson": 17,
    "textbook": "genki-2"
  },
  {
    "id": "genki-2-17-new-233",
    "japanese": "ショッピングモール",
    "reading": "",
    "meaning": "shopping mall",
    "jlptLevel": "N2",
    "partOfSpeech": [],
    "examples": [
      {
        "japanese": "ショッピングモール",
        "reading": "",
        "english": "17"
      }
    ],
    "tags": [
      "n2",
      "lesson-17",
      "genki-2"
    ],
    "lesson": 17,
    "textbook": "genki-2"
  },
  {
    "id": "genki-2-17-new-234",
    "japanese": "寮",
    "reading": "りょう",
    "meaning": "dormitory",
    "jlptLevel": "N5",
    "partOfSpeech": [],
    "examples": [
      {
        "japanese": "寮",
        "reading": "",
        "english": "17"
      }
    ],
    "tags": [
      "n5",
      "lesson-17",
      "genki-2"
    ],
    "lesson": 17,
    "textbook": "genki-2"
  },
  {
    "id": "genki-2-17-new-235",
    "japanese": "違い",
    "reading": "ちがい",
    "meaning": "difference",
    "jlptLevel": "N5",
    "partOfSpeech": [],
    "examples": [
      {
        "japanese": "違い",
        "reading": "",
        "english": "17"
      }
    ],
    "tags": [
      "n5",
      "lesson-17",
      "genki-2"
    ],
    "lesson": 17,
    "textbook": "genki-2"
  },
  {
    "id": "genki-2-17-new-236",
    "japanese": "秘密",
    "reading": "ひみつ",
    "meaning": "secret",
    "jlptLevel": "N5",
    "partOfSpeech": [],
    "examples": [
      {
        "japanese": "秘密",
        "reading": "",
        "english": "17"
      }
    ],
    "tags": [
      "n5",
      "lesson-17",
      "genki-2"
    ],
    "lesson": 17,
    "textbook": "genki-2"
  },
  {
    "id": "genki-2-17-new-237",
    "japanese": "準備",
    "reading": "じゅんび",
    "meaning": "preparation",
    "jlptLevel": "N5",
    "partOfSpeech": [],
    "examples": [
      {
        "japanese": "準備",
        "reading": "",
        "english": "17"
      }
    ],
    "tags": [
      "n5",
      "lesson-17",
      "genki-2"
    ],
    "lesson": 17,
    "textbook": "genki-2"
  },
  {
    "id": "genki-2-17-new-238",
    "japanese": "自分",
    "reading": "じぶん",
    "meaning": "oneself",
    "jlptLevel": "N5",
    "partOfSpeech": [],
    "examples": [
      {
        "japanese": "自分",
        "reading": "",
        "english": "17"
      }
    ],
    "tags": [
      "n5",
      "lesson-17",
      "genki-2"
    ],
    "lesson": 17,
    "textbook": "genki-2"
  },
  {
    "id": "genki-2-17-new-239",
    "japanese": "危ない",
    "reading": "あぶない",
    "meaning": "dangerous",
    "jlptLevel": "N4",
    "partOfSpeech": [],
    "examples": [
      {
        "japanese": "危ない",
        "reading": "",
        "english": "17"
      }
    ],
    "tags": [
      "n4",
      "lesson-17",
      "genki-2"
    ],
    "lesson": 17,
    "textbook": "genki-2"
  },
  {
    "id": "genki-2-17-new-240",
    "japanese": "羨ましい",
    "reading": "うらやましい",
    "meaning": "envious",
    "jlptLevel": "N4",
    "partOfSpeech": [],
    "examples": [
      {
        "japanese": "羨ましい",
        "reading": "",
        "english": "17"
      }
    ],
    "tags": [
      "n4",
      "lesson-17",
      "genki-2"
    ],
    "lesson": 17,
    "textbook": "genki-2"
  },
  {
    "id": "genki-2-17-new-241",
    "japanese": "少ない",
    "reading": "すくない",
    "meaning": "a little; a few",
    "jlptLevel": "N4",
    "partOfSpeech": [],
    "examples": [
      {
        "japanese": "少ない",
        "reading": "",
        "english": "17"
      }
    ],
    "tags": [
      "n4",
      "lesson-17",
      "genki-2"
    ],
    "lesson": 17,
    "textbook": "genki-2"
  },
  {
    "id": "genki-2-17-new-242",
    "japanese": "都合が悪い",
    "reading": "つごうがわるい",
    "meaning": "inconvenient; to have a scheduling conflict",
    "jlptLevel": "N3",
    "partOfSpeech": [],
    "examples": [
      {
        "japanese": "都合が悪い",
        "reading": "",
        "english": "17"
      }
    ],
    "tags": [
      "n3",
      "lesson-17",
      "genki-2"
    ],
    "lesson": 17,
    "textbook": "genki-2"
  },
  {
    "id": "genki-2-17-new-243",
    "japanese": "強い",
    "reading": "つよい",
    "meaning": "strong",
    "jlptLevel": "N5",
    "partOfSpeech": [],
    "examples": [
      {
        "japanese": "強い",
        "reading": "",
        "english": "17"
      }
    ],
    "tags": [
      "n5",
      "lesson-17",
      "genki-2"
    ],
    "lesson": 17,
    "textbook": "genki-2"
  },
  {
    "id": "genki-2-17-new-244",
    "japanese": "最悪",
    "reading": "さいあく(な)",
    "meaning": "the worst",
    "jlptLevel": "N5",
    "partOfSpeech": [],
    "examples": [
      {
        "japanese": "最悪",
        "reading": "",
        "english": "17"
      }
    ],
    "tags": [
      "n5",
      "lesson-17",
      "genki-2"
    ],
    "lesson": 17,
    "textbook": "genki-2"
  },
  {
    "id": "genki-2-17-new-245",
    "japanese": "選ぶ",
    "reading": "えらぶ",
    "meaning": "to choose; to select (～を)",
    "jlptLevel": "N5",
    "partOfSpeech": [],
    "examples": [
      {
        "japanese": "選ぶ",
        "reading": "",
        "english": "17"
      }
    ],
    "tags": [
      "n5",
      "lesson-17",
      "genki-2"
    ],
    "lesson": 17,
    "textbook": "genki-2"
  },
  {
    "id": "genki-2-17-new-246",
    "japanese": "お湯を沸かす",
    "reading": "おゆをわかす",
    "meaning": "to boil water",
    "jlptLevel": "N3",
    "partOfSpeech": [],
    "examples": [
      {
        "japanese": "お湯を沸かす",
        "reading": "",
        "english": "17"
      }
    ],
    "tags": [
      "n3",
      "lesson-17",
      "genki-2"
    ],
    "lesson": 17,
    "textbook": "genki-2"
  },
  {
    "id": "genki-2-17-new-247",
    "japanese": "髪をとかす",
    "reading": "かみをとかす",
    "meaning": "to comb one's hair",
    "jlptLevel": "N3",
    "partOfSpeech": [],
    "examples": [
      {
        "japanese": "髪をとかす",
        "reading": "",
        "english": "17"
      }
    ],
    "tags": [
      "n3",
      "lesson-17",
      "genki-2"
    ],
    "lesson": 17,
    "textbook": "genki-2"
  },
  {
    "id": "genki-2-17-new-248",
    "japanese": "髭を剃る(rare)",
    "reading": "ひげをそる",
    "meaning": "to shave one's beard",
    "jlptLevel": "N2",
    "partOfSpeech": [],
    "examples": [
      {
        "japanese": "髭を剃る(rare)",
        "reading": "",
        "english": "17"
      }
    ],
    "tags": [
      "n2",
      "lesson-17",
      "genki-2"
    ],
    "lesson": 17,
    "textbook": "genki-2"
  },
  {
    "id": "genki-2-17-new-249",
    "japanese": "脱ぐ",
    "reading": "ぬぐ",
    "meaning": "to take off (clothes) (～を)",
    "jlptLevel": "N5",
    "partOfSpeech": [],
    "examples": [
      {
        "japanese": "脱ぐ",
        "reading": "",
        "english": "17"
      }
    ],
    "tags": [
      "n5",
      "lesson-17",
      "genki-2"
    ],
    "lesson": 17,
    "textbook": "genki-2"
  },
  {
    "id": "genki-2-17-new-250",
    "japanese": "混む",
    "reading": "こむ",
    "meaning": "to get crowded (～が)",
    "jlptLevel": "N5",
    "partOfSpeech": [],
    "examples": [
      {
        "japanese": "混む",
        "reading": "",
        "english": "17"
      }
    ],
    "tags": [
      "n5",
      "lesson-17",
      "genki-2"
    ],
    "lesson": 17,
    "textbook": "genki-2"
  },
  {
    "id": "genki-2-17-new-251",
    "japanese": "宝くじに当たる",
    "reading": "たからくじにあたる",
    "meaning": "to win a lottery",
    "jlptLevel": "N2",
    "partOfSpeech": [],
    "examples": [
      {
        "japanese": "宝くじに当たる",
        "reading": "",
        "english": "17"
      }
    ],
    "tags": [
      "n2",
      "lesson-17",
      "genki-2"
    ],
    "lesson": 17,
    "textbook": "genki-2"
  },
  {
    "id": "genki-2-17-new-252",
    "japanese": "入れる",
    "reading": "いれる",
    "meaning": "to make tea, coffee, etc. (～を)",
    "jlptLevel": "N4",
    "partOfSpeech": [],
    "examples": [
      {
        "japanese": "入れる",
        "reading": "",
        "english": "17"
      }
    ],
    "tags": [
      "n4",
      "lesson-17",
      "genki-2"
    ],
    "lesson": 17,
    "textbook": "genki-2"
  },
  {
    "id": "genki-2-17-new-253",
    "japanese": "生まれる",
    "reading": "うまれる",
    "meaning": "to be born (～が)",
    "jlptLevel": "N4",
    "partOfSpeech": [],
    "examples": [
      {
        "japanese": "生まれる",
        "reading": "",
        "english": "17"
      }
    ],
    "tags": [
      "n4",
      "lesson-17",
      "genki-2"
    ],
    "lesson": 17,
    "textbook": "genki-2"
  },
  {
    "id": "genki-2-17-new-254",
    "japanese": "鍵をかける",
    "reading": "かぎをかける",
    "meaning": "to lock (～に)",
    "jlptLevel": "N3",
    "partOfSpeech": [],
    "examples": [
      {
        "japanese": "鍵をかける",
        "reading": "",
        "english": "17"
      }
    ],
    "tags": [
      "n3",
      "lesson-17",
      "genki-2"
    ],
    "lesson": 17,
    "textbook": "genki-2"
  },
  {
    "id": "genki-2-17-new-255",
    "japanese": "足りる",
    "reading": "たりる",
    "meaning": "to be sufficient; to be enough (～が)",
    "jlptLevel": "N4",
    "partOfSpeech": [],
    "examples": [
      {
        "japanese": "足りる",
        "reading": "",
        "english": "17"
      }
    ],
    "tags": [
      "n4",
      "lesson-17",
      "genki-2"
    ],
    "lesson": 17,
    "textbook": "genki-2"
  },
  {
    "id": "genki-2-17-new-256",
    "japanese": "慣れる",
    "reading": "なれる",
    "meaning": "to get used to… (～に)",
    "jlptLevel": "N4",
    "partOfSpeech": [],
    "examples": [
      {
        "japanese": "慣れる",
        "reading": "",
        "english": "17"
      }
    ],
    "tags": [
      "n4",
      "lesson-17",
      "genki-2"
    ],
    "lesson": 17,
    "textbook": "genki-2"
  },
  {
    "id": "genki-2-17-new-257",
    "japanese": "お祈りする",
    "reading": "おいのりする",
    "meaning": "to pray (～に)",
    "jlptLevel": "N3",
    "partOfSpeech": [],
    "examples": [
      {
        "japanese": "お祈りする",
        "reading": "",
        "english": "17"
      }
    ],
    "tags": [
      "n3",
      "lesson-17",
      "genki-2"
    ],
    "lesson": 17,
    "textbook": "genki-2"
  },
  {
    "id": "genki-2-17-new-258",
    "japanese": "化粧する",
    "reading": "けしょうする",
    "meaning": "to put makeup on",
    "jlptLevel": "N4",
    "partOfSpeech": [],
    "examples": [
      {
        "japanese": "化粧する",
        "reading": "",
        "english": "17"
      }
    ],
    "tags": [
      "n4",
      "lesson-17",
      "genki-2"
    ],
    "lesson": 17,
    "textbook": "genki-2"
  },
  {
    "id": "genki-2-17-new-259",
    "japanese": "就職する",
    "reading": "しゅうしょくする",
    "meaning": "to get a full-time job (at) (companyに)",
    "jlptLevel": "N4",
    "partOfSpeech": [],
    "examples": [
      {
        "japanese": "就職する",
        "reading": "",
        "english": "17"
      }
    ],
    "tags": [
      "n4",
      "lesson-17",
      "genki-2"
    ],
    "lesson": 17,
    "textbook": "genki-2"
  },
  {
    "id": "genki-2-17-new-260",
    "japanese": "離婚する",
    "reading": "りこんする",
    "meaning": "to get a divorce (personと)",
    "jlptLevel": "N4",
    "partOfSpeech": [],
    "examples": [
      {
        "japanese": "離婚する",
        "reading": "",
        "english": "17"
      }
    ],
    "tags": [
      "n4",
      "lesson-17",
      "genki-2"
    ],
    "lesson": 17,
    "textbook": "genki-2"
  },
  {
    "id": "genki-2-17-new-261",
    "japanese": "（e.g. ネクタイをする)",
    "reading": "する",
    "meaning": "to wear small items (necktie, watch, etc.) (～を)",
    "jlptLevel": "N2",
    "partOfSpeech": [],
    "examples": [
      {
        "japanese": "（e.g. ネクタイをする)",
        "reading": "",
        "english": "17"
      }
    ],
    "tags": [
      "n2",
      "lesson-17",
      "genki-2"
    ],
    "lesson": 17,
    "textbook": "genki-2"
  },
  {
    "id": "genki-2-17-new-262",
    "japanese": "随分(rare)",
    "reading": "ずいぶん",
    "meaning": "very",
    "jlptLevel": "N2",
    "partOfSpeech": [],
    "examples": [
      {
        "japanese": "随分(rare)",
        "reading": "",
        "english": "17"
      }
    ],
    "tags": [
      "n2",
      "lesson-17",
      "genki-2"
    ],
    "lesson": 17,
    "textbook": "genki-2"
  },
  {
    "id": "genki-2-17-new-263",
    "japanese": "例えば",
    "reading": "たとえば",
    "meaning": "for example",
    "jlptLevel": "N4",
    "partOfSpeech": [],
    "examples": [
      {
        "japanese": "例えば",
        "reading": "",
        "english": "17"
      }
    ],
    "tags": [
      "n4",
      "lesson-17",
      "genki-2"
    ],
    "lesson": 17,
    "textbook": "genki-2"
  },
  {
    "id": "genki-2-17-new-264",
    "japanese": "～に比べて",
    "reading": "～にくらべて",
    "meaning": "compared with…",
    "jlptLevel": "N3",
    "partOfSpeech": [],
    "examples": [
      {
        "japanese": "～に比べて",
        "reading": "",
        "english": "17"
      }
    ],
    "tags": [
      "n3",
      "lesson-17",
      "genki-2"
    ],
    "lesson": 17,
    "textbook": "genki-2"
  }
]